bytesep/__init__.py
bytesep/__main__.py
bytesep/inference.py
bytesep/inference_many.py
bytesep/losses.py
bytesep/separate.py
bytesep/train.py
bytesep/utils.py
bytesep/callbacks/__init__.py
bytesep/callbacks/base_callbacks.py
bytesep/callbacks/instruments.py
bytesep/callbacks/instruments_callbacks.py
bytesep/callbacks/musdb18.py
bytesep/callbacks/voicebank_demand.py
bytesep/data/__init__.py
bytesep/data/augmentors.py
bytesep/data/batch_data_preprocessors.py
bytesep/data/data_modules.py
bytesep/data/samplers.py
bytesep/dataset_creation/__init__.py
bytesep/dataset_creation/create_evaluation_audios/__init__.py
bytesep/dataset_creation/create_evaluation_audios/piano-symphony.py
bytesep/dataset_creation/create_evaluation_audios/vctk-musdb18.py
bytesep/dataset_creation/create_evaluation_audios/violin-piano.py
bytesep/dataset_creation/create_indexes/__init__.py
bytesep/dataset_creation/create_indexes/_create_vctk_audioset_indexes.py
bytesep/dataset_creation/create_indexes/create_indexes.py
bytesep/dataset_creation/pack_audios_to_hdf5s/__init__.py
bytesep/dataset_creation/pack_audios_to_hdf5s/instruments_solo.py
bytesep/dataset_creation/pack_audios_to_hdf5s/maestro.py
bytesep/dataset_creation/pack_audios_to_hdf5s/musdb18.py
bytesep/dataset_creation/pack_audios_to_hdf5s/vctk.py
bytesep/dataset_creation/pack_audios_to_hdf5s/voicebank-demand.py
bytesep/models/__init__.py
bytesep/models/_ttnet.py
bytesep/models/_ttnet2.py
bytesep/models/conditional_unet.py
bytesep/models/levelrnn.py
bytesep/models/levelrnn2.py
bytesep/models/lightning_modules.py
bytesep/models/linear_transformer.py
bytesep/models/mobilenet_subbandtime.py
bytesep/models/pytorch_modules.py
bytesep/models/resunet.py
bytesep/models/resunet_ismir2021.py
bytesep/models/resunet_subbandtime.py
bytesep/models/ttnet.py
bytesep/models/ttnet_jiafeng.py
bytesep/models/ttnet_no_transformer.py
bytesep/models/unet.py
bytesep/models/unet_subbandtime.py
bytesep/models/wavunet.py
bytesep/models/wavunet_levelrnn.py
bytesep_fancybit-0.0.8.dist-info/LICENSE
bytesep_fancybit-0.0.8.dist-info/METADATA
bytesep_fancybit-0.0.8.dist-info/WHEEL
bytesep_fancybit-0.0.8.dist-info/top_level.txt
bytesep_fancybit-0.0.8.dist-info/RECORD
