Metadata-Version: 2.1
Name: bytesep-fancybit
Version: 0.0.8
Summary: Music source separation fancybit 2024
Home-page: https://github.com/fancybit/music_source_separation
Author: fancybit
Author-email: fancybit@qq.com
License: Apache 2.0
License-File: LICENSE
Requires-Dist: torch (==2.1.0)
Requires-Dist: librosa (==0.8.0)
Requires-Dist: museval (==0.4.0)
Requires-Dist: h5py (==2.10.0)
Requires-Dist: pytorch-lightning (==1.2.1)
Requires-Dist: numpy (==1.20.3)
Requires-Dist: torchlibrosa (==0.0.9)
Requires-Dist: matplotlib (==3.3.4)
Requires-Dist: musdb (==0.4.0)
Requires-Dist: inplace-abn (==1.1.0)
